dds.cpython-37m-x86_64-linux-gnu.so
ddsutil.py
ts_dds-6.9.190925.post7.dist-info/METADATA
ts_dds-6.9.190925.post7.dist-info/WHEEL
ts_dds-6.9.190925.post7.dist-info/top_level.txt
ts_dds-6.9.190925.post7.dist-info/RECORD
