Metadata-Version: 2.1
Name: ts-dds
Version: 6.9.190925.post7
Summary: A python implementation of the OMG DDS Data-Centric Publish-Subscribe (DCPS) API, for use with Vortex OpenSplice DDS middleware.
Home-page: http://vortex.adlinktech.com
Author: ADLINK Technology
Author-email: ist_support@adlinktech.com
License: UNKNOWN
Platform: UNKNOWN
